redturtle.volto-5.9.4-py3.11-nspkg.pth
redturtle/volto/__init__.py
redturtle/volto/catalogplan.py
redturtle/volto/configure.zcml
redturtle/volto/dependencies.zcml
redturtle/volto/events.py
redturtle/volto/indexers.py
redturtle/volto/indexers.zcml
redturtle/volto/interfaces.py
redturtle/volto/monkey.py
redturtle/volto/monkey.zcml
redturtle/volto/patches.py
redturtle/volto/permissions.zcml
redturtle/volto/setuphandlers.py
redturtle/volto/testing.py
redturtle/volto/upgrades.py
redturtle/volto/upgrades.zcml
redturtle/volto/adapters/__init__.py
redturtle/volto/adapters/blocks_linkintegrity.py
redturtle/volto/adapters/blocks_linkintegrity_blocksfield.py
redturtle/volto/adapters/configure.zcml
redturtle/volto/adapters/link_linkintegrity_retriever.py
redturtle/volto/adapters/namechooser.py
redturtle/volto/adapters/rss.py
redturtle/volto/adapters/stringinterp.py
redturtle/volto/browser/__init__.py
redturtle/volto/browser/configure.zcml
redturtle/volto/browser/controlpanel.py
redturtle/volto/browser/display_file.py
redturtle/volto/browser/find_blocks.pt
redturtle/volto/browser/find_blocks.py
redturtle/volto/browser/find_broken_links.py
redturtle/volto/browser/fix_links.pt
redturtle/volto/browser/fix_links.py
redturtle/volto/browser/item.pt
redturtle/volto/browser/noindex.pt
redturtle/volto/browser/sitemap.py
redturtle/volto/browser/templates/RSS.pt
redturtle/volto/browser/templates/document.pt
redturtle/volto/browser/templates/homepage_view.pt
redturtle/volto/browser/templates/voltobackendwarning.pt
redturtle/volto/config/__init__.py
redturtle/volto/locales/README.rst
redturtle/volto/locales/__init__.py
redturtle/volto/locales/redturtle.volto.pot
redturtle/volto/locales/update.py
redturtle/volto/locales/update.sh
redturtle/volto/locales/it/LC_MESSAGES/redturtle.volto.po
redturtle/volto/profiles/default/browserlayer.xml
redturtle/volto/profiles/default/catalog.xml
redturtle/volto/profiles/default/controlpanel.xml
redturtle/volto/profiles/default/metadata.xml
redturtle_volto-5.9.4.dist-info/licenses/LICENSE.GPL
redturtle_volto-5.9.4.dist-info/licenses/LICENSE.rst
redturtle_volto-5.9.4.dist-info/METADATA
redturtle_volto-5.9.4.dist-info/WHEEL
redturtle_volto-5.9.4.dist-info/entry_points.txt
redturtle_volto-5.9.4.dist-info/namespace_packages.txt
redturtle_volto-5.9.4.dist-info/top_level.txt
redturtle_volto-5.9.4.dist-info/RECORD
