Metadata-Version: 2.4
Name: redturtle.volto
Version: 5.9.4
Summary: Helper package to setup a RedTurtle's Plone site ready to work with Volto.
Home-page: https://github.com/collective/redturtle.volto
Author: RedTurtle Technology
Author-email: sviluppo@redturtle.it
License: GPL version 2
Project-URL: PyPI, https://pypi.python.org/pypi/redturtle.volto
Project-URL: Source, https://github.com/RedTurtle/redturtle.volto
Project-URL: Tracker, https://github.com/RedTurtle/redturtle.volto/issues
Keywords: Python Plone
Classifier: Development Status :: 5 - Production/Stable
Classifier: Environment :: Web Environment
Classifier: Framework :: Plone
Classifier: Framework :: Plone :: Addon
Classifier: Framework :: Plone :: 5.2
Classifier: Framework :: Plone :: 6.0
Classifier: Programming Language :: Python
Classifier: Programming Language :: Python :: 3.8
Classifier: Programming Language :: Python :: 3.9
Classifier: Programming Language :: Python :: 3.10
Classifier: Programming Language :: Python :: 3.11
Classifier: Operating System :: OS Independent
Classifier: License :: OSI Approved :: GNU General Public License v2 (GPLv2)
Requires-Python: >=3.7
License-File: LICENSE.GPL
License-File: LICENSE.rst
Requires-Dist: setuptools
Requires-Dist: collective.volto.gdprcookie
Requires-Dist: collective.monkeypatcher
Requires-Dist: collective.purgebyid
Requires-Dist: kitconcept.seo>=2.0.0
Requires-Dist: plone.volto>=4.0.0
Requires-Dist: plone.restapi>=9.6.0
Requires-Dist: Products.PortalTransforms>=3.2.0
Requires-Dist: collective.volto.sitesettings
Requires-Dist: experimental.noacquisition
Provides-Extra: advancedquery
Requires-Dist: dm.plone.advancedquery; extra == "advancedquery"
Provides-Extra: test
Requires-Dist: plone.app.testing; extra == "test"
Requires-Dist: plone.testing>=5.0.0; extra == "test"
Requires-Dist: plone.app.contenttypes; extra == "test"
Requires-Dist: plone.app.robotframework[debug]; extra == "test"
Requires-Dist: collective.MockMailHost; extra == "test"
Dynamic: author
Dynamic: author-email
Dynamic: classifier
Dynamic: description
Dynamic: home-page
Dynamic: keywords
Dynamic: license
Dynamic: license-file
Dynamic: project-url
Dynamic: provides-extra
Dynamic: requires-dist
Dynamic: requires-python
Dynamic: summary
